mcp_server_opensearch/__init__.py
mcp_server_opensearch/__main__.py
mcp_server_opensearch/clusters_information.py
mcp_server_opensearch/global_state.py
mcp_server_opensearch/stdio_server.py
mcp_server_opensearch/streaming_server.py
opensearch/__init__.py
opensearch/client.py
opensearch/connection.py
opensearch/helper.py
tools/__init__.py
tools/config.py
tools/generic_api_tool.py
tools/skills_tools.py
tools/tool_filter.py
tools/tool_generator.py
tools/tool_params.py
tools/tools.py
tools/utils.py
opensearch_mcp_server_py-0.7.0.dist-info/METADATA
opensearch_mcp_server_py-0.7.0.dist-info/WHEEL
opensearch_mcp_server_py-0.7.0.dist-info/entry_points.txt
opensearch_mcp_server_py-0.7.0.dist-info/top_level.txt
opensearch_mcp_server_py-0.7.0.dist-info/RECORD
