Metadata-Version: 2.4
Name: opensearch-mcp-server-py
Version: 0.7.0
Summary: OpenSearch MCP Server
License-Expression: Apache-2.0
Project-URL: Homepage, https://github.com/opensearch-project/opensearch-mcp-server-py
Project-URL: Documentation, https://github.com/opensearch-project/opensearch-mcp-server-py/blob/main/USER_GUIDE.md
Project-URL: Source, https://github.com/opensearch-project/opensearch-mcp-server-py.git
Project-URL: Bug Tracker, https://github.com/opensearch-project/opensearch-mcp-server-py/issues
Project-URL: Changelog, https://github.com/opensearch-project/opensearch-mcp-server-py/blob/main/CHANGELOG.md
Requires-Python: >=3.10
Requires-Dist: aiohttp>=3.11.18
Requires-Dist: boto3>=1.38.3
Requires-Dist: mcp[cli]>=1.9.4
Requires-Dist: opensearch-py==2.8.0
Requires-Dist: pydantic>=2.11.3
Requires-Dist: pyyaml>=6.0.2
Requires-Dist: requests-aws4auth>=1.3.1
Requires-Dist: semver>=3.0.4
